log_inspector/__init__.py
log_inspector/admin.py
log_inspector/apps.py
log_inspector/models.py
log_inspector/settings.py
log_inspector/tests.py
log_inspector/urls.py
log_inspector/utils.py
log_inspector/views.py
log_inspector/migrations/__init__.py
log_inspector/static/log_inspector/css/input.css
log_inspector/static/log_inspector/css/output.css
log_inspector/static/log_inspector/js/alpinejs.min.js
log_inspector/static/log_inspector/js/htmx.min.js
log_inspector/templates/log_inspector/home.html
log_inspector/templates/log_inspector/log_entries_data.html
log_inspector/templates/log_inspector/log_entries_table.html
log_inspector/templates/log_inspector/log_files.html
log_inspector/templates/log_inspector/pagination.html
log_inspector/templates/log_inspector/start_live.html
django_log_inspector-0.0.9.dist-info/LICENSE
django_log_inspector-0.0.9.dist-info/METADATA
django_log_inspector-0.0.9.dist-info/WHEEL
django_log_inspector-0.0.9.dist-info/top_level.txt
django_log_inspector-0.0.9.dist-info/RECORD
