Metadata-Version: 2.1
Name: django-log-inspector
Version: 0.0.9
Summary: Real-Time monitoring and analysis of logs
Author-email: Peyman Hassani <hassani.peyman627@gmail.com>, Shaghayegh Valadkhani <valadkhani.sh@gmail.com>
Maintainer-email: Peyman Hassani <hassani.peyman627@gmail.com>, Shaghayegh Valadkhani <valadkhani.sh@gmail.com>
License: MIT License
Project-URL: Homepage, https://github.com/peyzor/django-log-inspector
Keywords: Django,logging,log viewer,real-time monitoring,log analysis,troubleshooting,log management,log files,log monitoring,debugging,Python web development,development tool
License-File: LICENSE
